setup.py
zesty_poker/__init__.py
zesty_poker/card.py
zesty_poker/deck.py
zesty_poker/evaluator.py
zesty_poker/lookup.py
zesty_poker.egg-info/PKG-INFO
zesty_poker.egg-info/SOURCES.txt
zesty_poker.egg-info/dependency_links.txt
zesty_poker.egg-info/top_level.txt